trifle/__init__.py
trifle/ast.py
trifle-0.1.0.dist-info/LICENSE
trifle-0.1.0.dist-info/METADATA
trifle-0.1.0.dist-info/WHEEL
trifle-0.1.0.dist-info/RECORD
